{"Allentown": 0, "Charlotte": 1, "Philadelphia": 2, "Abilene": 3, "Dallas-Fort Worth": 4, "Albuquerque": 5, "Los Angeles": 6, "Chicago": 7, "Phoenix": 8, "Aberdeen": 9, "London": 10, "Accra": 11, "Waco": 12, "Adelaide": 13, "Brisbane": 14, "Sydney": 15, "Alexandria": 16, "Malaga": 17, "Bush Field": 18, "Washington": 19, "Aguascalientes": 20, "Auckland": 21, "Papeete": 22, "Albany": 23, "Waterloo": 24, "Amarillo": 25, "Amman": 26, "New York": 27, "Montreal": 28, "Amsterdam": 29, "Anchorage": 30, "Antigua": 31, "Miami": 32, "Arequipa": 33, "Lima": 34, "Stockholm": 35, "Watertown": 36, "Alice Springs": 37, "Asuncion": 38, "Athens": 39, "Atlanta": 40, "Oranjestad": 41, "Abu Dhabi": 42, "Colombo": 43, "Duesseldorf": 44, "Islamabad": 45, "Lahore": 46, "Muscat": 47, "Austin": 48, "New Orleans": 49, "Asheville": 50, "Scranton": 51, "Kalamazoo": 52, "Bahrain": 53, "Doha": 54, "Barcelona": 55, "Bermuda": 56, "Windsor Locks": 57, "Pittsburgh": 58, "Bakersfield": 59, "Bridgetown": 60, "Binghamton": 61, "Bergen": 62, "Bangor": 63, "Belfast": 64, "Birmingham": 65, "Banjul": 66, "Dakar": 67, "Del Bajio": 68, "Bangkok": 69, "Kuala Lumpur": 70, "Tokyo": 71, "Bologna": 72, "Bangalore": 73, "Bloomington": 74, "Nashville": 75, "Canberra": 76, "Cairns": 77, "Darwin": 78, "Melbourne": 79, "Perth": 80, "Townsville": 81, "Bogota": 82, "Boise": 83, "Mumbai": 84, "Boston": 85, "Buffalo": 86, "Cancun": 87, "Madrid": 88, "Harrisburg": 89, "Portland": 90, "Richmond": 91, "Rochester": 92, "San Diego": 93, "Seattle": 94, "Syracuse": 95, "Beaumont": 96, "Brownsville": 97, "Brussels": 98, "Brasilia": 99, "Basel": 100, "Baton Rouge": 101, "Burlington": 102, "Budapest": 103, "Burbank": 104, "Baltimore": 105, "Belize City": 106, "Columbia": 107, "Akron": 108, "Caracas": 109, "San Juan": 110, "Paris": 111, "Chattanooga": 112, "Christchurch": 113, "Charlottesville VA": 114, "Charleston": 115, "Cedar Rapids": 116, "Cleveland": 117, "College Station": 118, "Cali": 119, "Columbus": 120, "Cincinnati": 121, "Cozumel": 122, "Daytona Beach": 123, "Dayton": 124, "Denver": 125, "Des Moines": 126, "Detroit": 127, "Dublin": 128, "New Bern": 129, "Newark": 130, "Fayetteville": 131, "Rome": 132, "Fort Lauderdale": 133, "Florence": 134, "Freeport": 135, "Frankfurt": 136, "Georgetown": 137, "Gainesville": 138, "Gulfport": 139, "Sao Paulo": 140, "Greensboro": 141, "Greenville": 142, "Hilton Head": 143, "White Plains": 144, "Huntsville": 145, "Huntington": 146, "Houston": 147, "Wilmington": 148, "Indianapolis": 149, "Jackson": 150, "Jacksonville": 151, "Las Vegas": 152, "Lexington KY": 153, "Liberia": 154, "Little Rock": 155, "Lynchburg": 156, "Montego Bay": 157, "Kansas City": 158, "Orlando": 159, "Memphis": 160, "Mexico City": 161, "MONTGOMERY": 162, "Manchester NH": 163, "Milwaukee": 164, "Mobile": 165, "Minneapolis": 166, "Myrtle Beach": 167, "Nassau": 168, "Jacksonville NC": 169, "Omaha": 170, "Norfolk": 171, "West Palm Beach": 172, "Newport News": 173, "Providenciales": 174, "Pensacola": 175, "Punta Cana": 176, "Providence": 177, "Raleigh-durham": 178, "Roanoke VA": 179, "Fort Myers": 180, "San Antonio": 181, "Savannah": 182, "Salisbury": 183, "Louisville": 184, "San Francisco": 185, "San Jose Del Cabo": 186, "San Jose": 187, "Salt Lake City": 188, "Sacramento": 189, "Sarasota": 190, "St. Louis": 191, "St. Thomas": 192, "Philipsburg": 193, "Tallahassee": 194, "Tampa": 195, "BRISTOL": 196, "Knoxville": 197, "Hewandorra": 198, "Valparaiso": 199, "Bentonville": 200, "Ottawa": 201, "Toronto": 202, "Champaign": 203, "Belo Horizonte": 204, "Colorado Springs": 205, "Copenhagen": 206, "Cape Town": 207, "Corpus Christi": 208, "Sapporo": 209, "Willemstad": 210, "Chihuahua": 211, "Wassau": 212, "Curitiba": 213, "Porto Alegre": 214, "Dubuque IA": 215, "Islip": 216, "Halifax": 217, "Delhi": 218, "Durango": 219, "El Paso": 220, "Evansville": 221, "Buenos Aires": 222, "Fargo": 223, "Fresno": 224, "Sioux Falls": 225, "Fort Smith": 226, "Fort Wayne": 227, "Garden City": 228, "Guadalajara": 229, "Longview": 230, "Rio De Janeiro": 231, "Grand Junction": 232, "Grand Island": 233, "Killeen": 234, "Grand Rapids": 235, "Guatemala City": 236, "Honolulu": 237, "Seoul": 238, "Wichita": 239, "Joplin": 240, "Lawton": 241, "Lubbock": 242, "Lake Charles": 243, "Lafayette": 244, "Laredo": 245, "Midland": 246, "Mcallen": 247, "Manhattan": 248, "Moline": 249, "Morelia": 250, "Monroe": 251, "Madison": 252, "Monterrey": 253, "Mazatlan": 254, "Kahului": 255, "Oklahoma City": 256, "Ontario": 257, "Puebla": 258, "Peoria": 259, "Palm Springs": 260, "Panama City": 261, "Puerto Vallarta": 262, "Queretaro": 263, "Rapid City": 264, "Reno": 265, "Roswell": 266, "Roatan": 267, "Santa Fe": 268, "San Salvador": 269, "Santiago": 270, "Springfield": 271, "Shreveport": 272, "San Angelo": 273, "San Luis Potosi": 274, "Santa Ana": 275, "Wichita Falls": 276, "Torreon": 277, "Tulsa": 278, "Tucson": 279, "Texarkana": 280, "Tyler": 281, "Edmonton": 282, "Vancouver": 283, "Calgary": 284, "Zacatecas": 285, "Gran Canaria": 286, "Dominica": 287, "Dubai": 288, "Entebbe": 289, "Edinburgh": 290, "Tortola": 291, "North Eleuthera": 292, "Elmira": 293, "Erie": 294, "Eugene": 295, "Hong Kong": 296, "Key West": 297, "Fort-de-france": 298, "Flagstaff": 299, "Port-au-prince": 300, "Flint": 301, "Fukuoka": 302, "Spokane": 303, "Great Exuma": 304, "Gibraltar": 305, "Glasgow": 306, "Point Salines": 307, "Gothenborg": 308, "Green Bay": 309, "Geneva": 310, "Guayaquil": 311, "San Crist\u00f3bal": 312, "Quito": 313, "Hannover": 314, "Hamburg": 315, "Hanoi": 316, "Helsinki": 317, "Manchester": 318, "Hermosillo": 319, "Osaka": 320, "Nagoya": 321, "Oakland": 322, "New Haven": 323, "Williamsport": 324, "Istanbul": 325, "Ithaca": 326, "Milano": 327, "Berlin": 328, "Zurich": 329, "Johannesburg": 330, "Juneau": 331, "Ketchikan": 332, "Juliaca": 333, "Kaohsiung": 334, "Kingston": 335, "Kona": 336, "Pulau": 337, "Penang": 338, "Singapore": 339, "Kuwait": 340, "Lihue": 341, "Medford": 342, "Mammoth Lakes": 343, "Monterey": 344, "Nandi": 345, "Shanghai": 346, "Redmond-Bend": 347, "Santa Rosa": 348, "Leeds": 349, "Larnaca": 350, "Long Beach": 351, "Milan": 352, "Lisbon": 353, "Luxemburg": 354, "Lyon": 355, "Madras": 356, "Marseille": 357, "Munich": 358, "Nairobi": 359, "Nice": 360, "Newcastle": 361, "Oslo": 362, "Bucharest": 363, "Prague": 364, "Pisa": 365, "Rotterdam": 366, "Sofia": 367, "Stuttgart": 368, "Stavanger": 369, "Toulouse": 370, "Venice": 371, "Vienna": 372, "Warsaw": 373, "Zagreb": 374, "La Paz": 375, "Santa Cruz": 376, "La Romana": 377, "La Crosse": 378, "Manaus": 379, "Maracaibo": 380, "Rio Negro": 381, "Managua": 382, "Marsh Harbor": 383, "Montevideo": 384, "Puerto Plata": 385, "Port-of-spain": 386, "Pointe-a-pitre": 387, "Recife": 388, "San Pedro Sula": 389, "Santo Domingo": 390, "Basse Terre": 391, "Salvador": 392, "St. Croix Island": 393, "Tegucigalpa": 394, "Marquette": 395, "Busan": 396, "Ho Chi Minh City": 397, "Taipei": 398, "Beijing": 399, "Sioux City": 400, "Toledo": 401, "Traverse City": 402, "State College Pennsylvania": 403, "Newburgh": 404, "Tel-aviv": 405, "Quebec": 406, "Santa Barbara": 407, "San Luis Obispo": 408, "Yuma": 409, "Zihuatanejo": 410, "Puerto Montt": 411, "Punta Arenas": 412, "Spanish Town": 413, "Vieques Island": 414}